flowfunnel/__init__.py
flowfunnel/cli.py
flowfunnel/dataloaders/__init__.py
flowfunnel/dataloaders/base.py
flowfunnel/dataloaders/download_hdfs.py
flowfunnel/dataloaders/generate_date_pairs.py
flowfunnel/dataloaders/load_csv.py
flowfunnel/dataloaders/load_dataframe.py
flowfunnel/dataloaders/load_hdfs.py
flowfunnel/dataloaders/load_tsv.py
flowfunnel/dataloaders/standardize.py
flowfunnel/dataloaders/upload_hdfs.py
flowfunnel/funnels/__init__.py
flowfunnel/funnels/pyro_funnel.py
flowfunnel/layers/ARn_pyro.py
flowfunnel/layers/__init__.py
flowfunnel/layers/base_pyro.py
flowfunnel/parallel/__init__.py
flowfunnel/parallel/logical_processors.py
flowfunnel/parallel/mpi_and_parallel_params.py
flowfunnel/visualization/__init__.py
flowfunnel/visualization/plot_rolling_window.py
flowfunnel-0.1.7.dist-info/LICENSE
flowfunnel-0.1.7.dist-info/METADATA
flowfunnel-0.1.7.dist-info/WHEEL
flowfunnel-0.1.7.dist-info/entry_points.txt
flowfunnel-0.1.7.dist-info/top_level.txt
flowfunnel-0.1.7.dist-info/RECORD
