Metadata-Version: 2.1
Name: flowfunnel
Version: 0.1.7
Summary: Leveraging Bayesian hierarchical models to diagnose issues and proactively predict user flow stages in conversion funnels.
Home-page: https://github.com/yinsn/FlowFunnel
Author: Yin Cheng
Author-email: yin.sjtu@gmail.com
Requires-Python: >=3.8
License-File: LICENSE
Requires-Dist: click >=8.1.3
Requires-Dist: imageio >=2.33.0
Requires-Dist: jax >=0.4.14
Requires-Dist: joblib >=1.3.2
Requires-Dist: matplotlib >=3.7.1
Requires-Dist: mpi4py >=3.1.5
Requires-Dist: numpyro >=0.12.0
Requires-Dist: pandas >=2.0.3
Requires-Dist: pyarrow >=14.0.1
Requires-Dist: tqdm >=4.66.1
